<?xml version="1.0"?>
<!--<!DOCTYPE metadata SYSTEM "http://www.esri.com/metadata/esriprof80.dtd">-->
<metadata xml:lang="en"><Esri><CreaDate>20151021</CreaDate><CreaTime>09060500</CreaTime><SyncOnce>TRUE</SyncOnce><DataProperties><lineage><Process ToolSource="C:\Program Files (x86)\ArcGIS\ArcToolbox\Toolboxes\Data Management Tools.tbx\DefineProjection" Date="20130726" Time="190907">DefineProjection NA_LandCover_2010_25haMMU.img PROJCS['Sphere_ARC_INFO_Lambert_Azimuthal_Equal_Area',GEOGCS['GCS_Sphere_ARC_INFO',DATUM['D_Sphere_ARC_INFO',SPHEROID['Sphere_ARC_INFO',6370997.0,0.0]],PRIMEM['Greenwich',0.0],UNIT['Degree',0.0174532925199433]],PROJECTION['Lambert_Azimuthal_Equal_Area'],PARAMETER['False_Easting',0.0],PARAMETER['False_Northing',0.0],PARAMETER['Central_Meridian',-100.0],PARAMETER['Latitude_Of_Origin',45.0],UNIT['Meter',1.0]] NA_LandCover_2010_25haMMU.img</Process></lineage></DataProperties><ArcGISFormat>1.0</ArcGISFormat></Esri></metadata>
